NiukeQianduanGangMianshiQiuzhiZhentiJiexi20212022Fix1/README.md
NiukeQianduanGangMianshiQiuzhiZhentiJiexi20212022Fix1/__init__.py
NiukeQianduanGangMianshiQiuzhiZhentiJiexi20212022Fix1/__main__.py
NiukeQianduanGangMianshiQiuzhiZhentiJiexi20212022Fix1/file.epub
NiukeQianduanGangMianshiQiuzhiZhentiJiexi20212022Fix1/index.html
NiukeQianduanGangMianshiQiuzhiZhentiJiexi20212022Fix1/css/__init__.py
NiukeQianduanGangMianshiQiuzhiZhentiJiexi20212022Fix1/css/annotations.css
NiukeQianduanGangMianshiQiuzhiZhentiJiexi20212022Fix1/css/main.css
NiukeQianduanGangMianshiQiuzhiZhentiJiexi20212022Fix1/css/normalize.css
NiukeQianduanGangMianshiQiuzhiZhentiJiexi20212022Fix1/css/popup.css
NiukeQianduanGangMianshiQiuzhiZhentiJiexi20212022Fix1/font/__init__.py
NiukeQianduanGangMianshiQiuzhiZhentiJiexi20212022Fix1/font/fontello.eot
NiukeQianduanGangMianshiQiuzhiZhentiJiexi20212022Fix1/font/fontello.svg
NiukeQianduanGangMianshiQiuzhiZhentiJiexi20212022Fix1/font/fontello.ttf
NiukeQianduanGangMianshiQiuzhiZhentiJiexi20212022Fix1/font/fontello.woff
NiukeQianduanGangMianshiQiuzhiZhentiJiexi20212022Fix1/img/__init__.py
NiukeQianduanGangMianshiQiuzhiZhentiJiexi20212022Fix1/img/annotator-glyph-sprite.png
NiukeQianduanGangMianshiQiuzhiZhentiJiexi20212022Fix1/img/annotator-icon-sprite.png
NiukeQianduanGangMianshiQiuzhiZhentiJiexi20212022Fix1/img/apple-touch-icon.png
NiukeQianduanGangMianshiQiuzhiZhentiJiexi20212022Fix1/img/cancelfullscreen.png
NiukeQianduanGangMianshiQiuzhiZhentiJiexi20212022Fix1/img/close.png
NiukeQianduanGangMianshiQiuzhiZhentiJiexi20212022Fix1/img/fullscreen.png
NiukeQianduanGangMianshiQiuzhiZhentiJiexi20212022Fix1/img/loader.gif
NiukeQianduanGangMianshiQiuzhiZhentiJiexi20212022Fix1/img/menu-icon.png
NiukeQianduanGangMianshiQiuzhiZhentiJiexi20212022Fix1/img/save.png
NiukeQianduanGangMianshiQiuzhiZhentiJiexi20212022Fix1/img/saved.png
NiukeQianduanGangMianshiQiuzhiZhentiJiexi20212022Fix1/img/settings-s.png
NiukeQianduanGangMianshiQiuzhiZhentiJiexi20212022Fix1/img/settings.png
niuke_qianduan_gang_mianshi_qiuzhi_zhenti_jiexi_2021_2022_fix1-2025.3.25.0.dist-info/METADATA
niuke_qianduan_gang_mianshi_qiuzhi_zhenti_jiexi_2021_2022_fix1-2025.3.25.0.dist-info/WHEEL
niuke_qianduan_gang_mianshi_qiuzhi_zhenti_jiexi_2021_2022_fix1-2025.3.25.0.dist-info/entry_points.txt
niuke_qianduan_gang_mianshi_qiuzhi_zhenti_jiexi_2021_2022_fix1-2025.3.25.0.dist-info/top_level.txt
niuke_qianduan_gang_mianshi_qiuzhi_zhenti_jiexi_2021_2022_fix1-2025.3.25.0.dist-info/RECORD
